flask_praetorian/__init__.py
flask_praetorian/base.py
flask_praetorian/constants.py
flask_praetorian/decorators.py
flask_praetorian/exceptions.py
flask_praetorian/templates/registration_email.html
flask_praetorian/templates/reset_email.html
flask_praetorian/user_mixins.py
flask_praetorian/utilities.py
flask_praetorian-1.6.2.dist-info/LICENSE.rst
flask_praetorian-1.6.2.dist-info/METADATA
flask_praetorian-1.6.2.dist-info/WHEEL
flask_praetorian-1.6.2.dist-info/RECORD
