Metadata-Version: 2.1
Name: flask-praetorian
Version: 1.6.2
Summary: Strong, Simple, and Precise security for Flask APIs (using jwt)
Home-page: https://flask-praetorian.readthedocs.io/en/latest/
License: MIT
Author: Tucker Beck
Author-email: tucker.beck@gmail.com
Requires-Python: >=3.8,<4.0
Classifier: License :: OSI Approved :: MIT License
Classifier: Programming Language :: Python :: 3
Classifier: Programming Language :: Python :: 3.8
Classifier: Programming Language :: Python :: 3.9
Classifier: Programming Language :: Python :: 3.10
Classifier: Programming Language :: Python :: 3.11
Requires-Dist: flask (>=2.0,<4.0)
Requires-Dist: flask-buzz (>=3.1,<4.0)
Requires-Dist: flask-mailman (>=1.0.0,<2.0.0)
Requires-Dist: passlib (>=1.7,<2.0)
Requires-Dist: pendulum (>=3.0,<4.0)
Requires-Dist: pyjwt (>=2.0,<3.0)
Project-URL: Documentation, https://flask-praetorian.readthedocs.io/en/latest/
Project-URL: Repository, https://github.com/dusktreader/flask-praetorian
